ezlaunch-1.2.4.data/scripts/ezlaunch
ezlaunch-1.2.4.data/scripts/getjid
ezlaunch-1.2.4.data/scripts/jfile
ezlaunch-1.2.4.data/scripts/jstatus
ezlaunch-1.2.4.data/scripts/launch
ezlaunch-1.2.4.data/scripts/rlaunch
ezlaunch-1.2.4.data/scripts/runexec
ezlaunch-1.2.4.data/scripts/slaunch
ezlaunch-1.2.4.data/scripts/subjexec
ezlaunch-1.2.4.data/scripts/subjids
launch/__init__.py
launch/config.py
ezlaunch-1.2.4.dist-info/LICENSE
ezlaunch-1.2.4.dist-info/METADATA
ezlaunch-1.2.4.dist-info/WHEEL
ezlaunch-1.2.4.dist-info/top_level.txt
ezlaunch-1.2.4.dist-info/RECORD
