Metadata-Version: 2.1
Name: ezlaunch
Version: 1.2.4
Summary: EZLaunch: Tools to run slurm jobs with launcher
Home-page: https://github.com/prestonlab/launch
Author: Neal Morton
Author-email: mortonne@gmail.com
License: GPL-3.0-or-later
Keywords: HPC,slurm,launcher
Classifier: Programming Language :: Python :: 3
Classifier: License :: OSI Approved :: GNU General Public License v3 or later (GPLv3+)
Classifier: Operating System :: OS Independent
License-File: LICENSE
Requires-Dist: toml
